carol_pdf_generator/__init__.py
carol_pdf_generator/carol_pdf_generator.py
carol_pdf_generator/docscan.py
carol_pdf_generator/transform.py
carol_pdf_generator-0.1.12.dist-info/AUTHORS.rst
carol_pdf_generator-0.1.12.dist-info/METADATA
carol_pdf_generator-0.1.12.dist-info/WHEEL
carol_pdf_generator-0.1.12.dist-info/top_level.txt
carol_pdf_generator-0.1.12.dist-info/RECORD
