Metadata-Version: 2.1
Name: carol-pdf-generator
Version: 0.1.12
Summary: A library to create PDF Files from a set of image files/base64 data
Home-page: https://github.com/gzamboni/carol_pdf_generator
Author: Giovani Zamboni
Author-email: giovani.zamboni@totvs.com
License: UNKNOWN
Keywords: carol_pdf_generator
Platform: UNKNOWN
Classifier: Development Status :: 2 - Pre-Alpha
Classifier: Intended Audience :: Developers
Classifier: Natural Language :: English
Classifier: Programming Language :: Python :: 3
Classifier: Programming Language :: Python :: 3.6
Classifier: Programming Language :: Python :: 3.7
Classifier: Programming Language :: Python :: 3.8
Requires-Python: >=3.6
Requires-Dist: python-datauri (==0.2.9)
Requires-Dist: reportbro-fpdf (==1.7.10)
Requires-Dist: opencv-contrib-python-headless
Requires-Dist: scikit-image
Requires-Dist: numpy
Requires-Dist: imutils
Requires-Dist: pypdf2
Requires-Dist: pikepdf
